kmongo.py
kmongo-0.2.dist-info/entry_points.txt
kmongo-0.2.dist-info/WHEEL
kmongo-0.2.dist-info/METADATA
kmongo-0.2.dist-info/RECORD
