Metadata-Version: 2.1
Name: kmongo
Version: 0.2
Summary: pymongo连接池
Keywords: 
Author-email: jutooy <jutooy@qq.com>
Classifier: License :: OSI Approved :: Apache Software License
